{
  "version": "1.0.0",
  "generatedAt": "2026-06-03T15:46:58.343Z",
  "totals": {
    "files": 180,
    "issues": 2
  },
  "coverage": {
    "docs": {
      "title": 1,
      "description": 1,
      "keywords": 1
    },
    "blog": {
      "title": 1,
      "description": 1,
      "keywords": 1
    },
    "all": {
      "title": 1,
      "description": 1,
      "keywords": 1
    }
  },
  "issueTypes": {
    "few_keywords": 2
  },
  "issues": [
    {
      "type": "few_keywords",
      "file": "quick-start/install.mdx",
      "message": "keywords 数量偏少（7）",
      "scope": "docs"
    },
    {
      "type": "few_keywords",
      "file": "tailwindcss/v5-official-plugin-parity.mdx",
      "message": "keywords 数量偏少（6）",
      "scope": "docs"
    }
  ]
}
